<?xml version='1.0' encoding='UTF-8'?>
<types:mule xmlns:types="http://www.mulesoft.org/schema/mule/types">
  <types:catalog>
    <types:type name="a" format="java">
      <types:shape format="raml"><![CDATA[#%RAML 1.0 DataType
type: string]]></types:shape>
    </types:type>
  </types:catalog>
  <types:enrichment select="#b145b593-24f3-49d0-9728-0310b38bddae">
    <types:processor-declaration>
      <types:input-event>
        <types:message>
          <types:payload type="a"/>
        </types:message>
      </types:input-event>
    </types:processor-declaration>
  </types:enrichment>
</types:mule>